mpl_spaceplot-0.2.1.dist-info/licenses/LICENSE
spaceplot/__init__.py
spaceplot/aligner.py
spaceplot/montage_plot.py
spaceplot/simulate_data.py
spaceplot/utils.py
spaceplot/appearance/__init__.py
spaceplot/appearance/display.py
spaceplot/appearance/inline.py
spaceplot/appearance/layout.py
spaceplot/appearance/palettes.py
spaceplot/appearance/styles.py
spaceplot/appearance/tools.py
spaceplot/decorators/__init__.py
spaceplot/decorators/decorators.py
spaceplot/decorators/tools.py
spaceplot/plotting/__init__.py
spaceplot/plotting/plotting.py
spaceplot/plotting/tools.py
spaceplot/resources/font_loader.py
spaceplot/resources/fonts/FiraCode/FiraCode-Bold.ttf
spaceplot/resources/fonts/FiraCode/FiraCode-Light.ttf
spaceplot/resources/fonts/FiraCode/FiraCode-Medium.ttf
spaceplot/resources/fonts/FiraCode/FiraCode-Regular.ttf
spaceplot/resources/fonts/FiraCode/FiraCode-SemiBold.ttf
spaceplot/resources/fonts/FiraMath/FiraMath-Bold.ttf
spaceplot/resources/fonts/FiraMath/FiraMath-ExtraLight.ttf
spaceplot/resources/fonts/FiraMath/FiraMath-Heavy.ttf
spaceplot/resources/fonts/FiraMath/FiraMath-Light.ttf
spaceplot/resources/fonts/FiraMath/FiraMath-Medium.ttf
spaceplot/resources/fonts/FiraMath/FiraMath-Regular.ttf
spaceplot/resources/fonts/FiraMath/FiraMath-SemiBold.ttf
spaceplot/resources/fonts/FiraMath/FiraMath-UltraLight.ttf
spaceplot/resources/fonts/FiraSans/FiraSans-Black.ttf
spaceplot/resources/fonts/FiraSans/FiraSans-BlackItalic.ttf
spaceplot/resources/fonts/FiraSans/FiraSans-Bold.ttf
spaceplot/resources/fonts/FiraSans/FiraSans-BoldItalic.ttf
spaceplot/resources/fonts/FiraSans/FiraSans-ExtraBold.ttf
spaceplot/resources/fonts/FiraSans/FiraSans-ExtraBoldItalic.ttf
spaceplot/resources/fonts/FiraSans/FiraSans-ExtraLight.ttf
spaceplot/resources/fonts/FiraSans/FiraSans-ExtraLightItalic.ttf
spaceplot/resources/fonts/FiraSans/FiraSans-Italic.ttf
spaceplot/resources/fonts/FiraSans/FiraSans-Light.ttf
spaceplot/resources/fonts/FiraSans/FiraSans-LightItalic.ttf
spaceplot/resources/fonts/FiraSans/FiraSans-Medium.ttf
mpl_spaceplot-0.2.1.dist-info/METADATA
mpl_spaceplot-0.2.1.dist-info/WHEEL
mpl_spaceplot-0.2.1.dist-info/top_level.txt
mpl_spaceplot-0.2.1.dist-info/RECORD
