Metadata-Version: 2.4
Name: mpl-spaceplot
Version: 0.2.1
Summary: layout wrappers for matplotlib
Author-email: Florian Raths <raths.f@gmail.com>
License: MIT
Keywords: matplotlib,plotting,wrappers
Classifier: Programming Language :: Python :: 3
Classifier: License :: OSI Approved :: MIT License
Classifier: Operating System :: OS Independent
Requires-Python: >=3.10
License-File: LICENSE
Requires-Dist: matplotlib>=3.7
Requires-Dist: cmcrameri>=1.9
Dynamic: license-file
